langchain_contextual/__init__.py
langchain_contextual/chat_models.py
langchain_contextual/py.typed
langchain_contextual/rerank.py
langchain_contextual-0.4.5.dist-info/LICENSE
langchain_contextual-0.4.5.dist-info/METADATA
langchain_contextual-0.4.5.dist-info/WHEEL
langchain_contextual-0.4.5.dist-info/RECORD
