Metadata-Version: 2.3
Name: langchain-contextual
Version: 0.4.5
Summary: An integration package connecting Contextual and LangChain
License: MIT
Requires-Python: >=3.9,<4.0
Classifier: License :: OSI Approved :: MIT License
Classifier: Programming Language :: Python :: 3
Classifier: Programming Language :: Python :: 3.9
Classifier: Programming Language :: Python :: 3.10
Classifier: Programming Language :: Python :: 3.11
Classifier: Programming Language :: Python :: 3.12
Classifier: Programming Language :: Python :: 3.13
Requires-Dist: contextual-client (>=0.4.0,<0.5.0)
Requires-Dist: langchain-core (>=0.3.15,<0.4.0)
Project-URL: Repository, https://github.com/ContextualAI/langchain-contextual
Project-URL: Release Notes, https://github.com/langchain-ai/langchain/releases?q=tag%3A%22contextual%3D%3D0%22&expanded=true
Project-URL: Source Code, https://github.com/ContextualAI/langchain-contextual
